{
  "title": "Double weight pocket soft, left, black  - Tecline",
  "code": "T01047-01",
  "price": 51.02,
  "currency": "EUR",
  "category": "products/tecline/buoyancy-control/components,2,5167",
  "photos": [
    {
      "src": "img/4667/kieszen-balastowa-podwojna-miekka-z-ruchomym-d-rin.jpg",
      "alt": "Kieszeń balastowa podwójna miękka z ruchomym d-ringiem, lewa, czarna - TecLine"
    }
  ],
  "description": "\n<h2>Product description</h2>\n(English version below)<br> <br> PL: <br> KIESZEŃ BALASTOWA MIĘKKA, LEWA <br> <br> OPIS:<br> - Kompaktowa kieszeń balastowa miękka z wkładem i ruchomym d-ringiem<br> - Niewielki rozmiar<br> - Maks. obciążenie: 3kg<br> - Duża klamra zatrzaskowa – łatwa w obsłudze nawet w grubych rękawicach<br> - W zestawie wkład na obciążenie, pozwalający na wygodny montaż balastu do kieszeni<br> - Kolor: czarny <br> <br> <br> ENG: SOFT POCKET LEFT <br> <br> DESCRIPTION:<br> - Compact, soft weight pocket with an insert and movable d-ring<br> - Small size<br> - Max. load: 3kg<br> - Large release buckle - easy to use even with thick gloves<br> - Weight insert included - for the convenient weights mounting<br> - Color: black <br>\n"
}