{
  "title": "Harness TecLine DIR adjustable standard webbing - incl. 6 mm SS backplate - weight 5,0 kg",
  "code": "T15013-01/T15015",
  "price": 282.24,
  "currency": "EUR",
  "category": "products/tecline/buoyancy-control/components,2,5167",
  "photos": [
    {
      "src": "img/1565/uprzaz-tecline-dir-regulowana-z-plyta-nierdzewna-6.jpg",
      "alt": "Uprząż Tecline DIR regulowana z płytą nierdzewną 6 mm, ruchome D-ringi, taśma standard - waga 5,0 kg"
    },
    {
      "src": "img/4522/harness-tecline-dir-adjustable-incl-6mm-ss-back.jpg",
      "alt": "Harness TecLine DIR adjustable standard webbing - incl. 6 mm SS backplate - weight 5,0 kg"
    }
  ],
  "description": "\n<h2>Product description</h2>\n<p style=\"text-align:left;margin:0pt 0pt 0pt 0pt\"><span style=\"font-family:Tahoma;font-size:10pt\">BACKPLATE + HARNESS SET</span></p><p style=\"text-align:left;margin:0pt 0pt 0pt 0pt\"><span style=\"font-family:Tahoma;font-size:10pt\">&nbsp;</span></p><p style=\"text-align:left;margin:0pt 0pt 0pt 0pt\"><span style=\"font-family:Tahoma;font-size:10pt\">The set includes:</span></p><p style=\"text-align:left;margin:0pt 0pt 0pt 0pt\"><span style=\"font-family:Tahoma;font-size:10pt\">- 6mm Stainless Steel Backplate (full, no logo, weight: 4,2kg)</span></p><p style=\"text-align:left;margin:0pt 0pt 0pt 0pt\"><span style=\"font-family:Tahoma;font-size:10pt\">- Tecline DIR Harness with chinch adapter, movable d-rings, standard webbing</span></p><p style=\"text-align:left;margin:0pt 0pt 0pt 0pt\"><span style=\"font-family:Tahoma;font-size:10pt\">- Crotch Strap</span></p>\n"
}