{
  "title": "TecLine Frameless View mask w/neoprene strap",
  "code": "T05050",
  "price": 52.83,
  "currency": "EUR",
  "category": "products/tecline/masks,2,3026",
  "photos": [
    {
      "src": "img/1967/maska-frameless-view-tecline-czarny-silikon-neop.jpg",
      "alt": "Maska Frameless View Tecline, czarny silikon, neoprenowy pasek"
    }
  ],
  "description": "\n<h2>Product description</h2>\nmaska bez ramki. bezpieczna szyba wykonana w technologii Anty-Fog. zwiększony kąt widzenia. niewielka pojemność wewnętrzna. miękki silikon doskonale przylegający do twarzy. neoprenowy pasek eliminujący problem pękniętego paska maski na nurkowaniu.\n"
}